dagster_pandas/__init__.py
dagster_pandas/constraints.py
dagster_pandas/data_frame.py
dagster_pandas/py.typed
dagster_pandas/validation.py
dagster_pandas/version.py
dagster_pandas/examples/__init__.py
dagster_pandas/examples/pandas_hello_world.yaml
dagster_pandas/examples/workspace.yaml
dagster_pandas/examples/pandas_hello_world/__init__.py
dagster_pandas/examples/pandas_hello_world/env.yaml
dagster_pandas/examples/pandas_hello_world/ops.py
dagster_pandas/examples/pandas_hello_world/solids.yaml
dagster_pandas/examples/pandas_hello_world/environments/pandas_hello_world_prod.yaml
dagster_pandas/examples/pandas_hello_world/environments/pandas_hello_world_test.yaml
dagster_pandas/examples/pandas_hello_world/environments/papermill_pandas_hello_world_prod.yaml
dagster_pandas/examples/pandas_hello_world/environments/papermill_pandas_hello_world_test.yaml
dagster_pandas-1.0.5.dist-info/LICENSE
dagster_pandas-1.0.5.dist-info/METADATA
dagster_pandas-1.0.5.dist-info/WHEEL
dagster_pandas-1.0.5.dist-info/top_level.txt
dagster_pandas-1.0.5.dist-info/RECORD
